ignutils/__init__.py
ignutils/algo_utils.py
ignutils/config_utils.py
ignutils/contour_utils.py
ignutils/crop_utils.py
ignutils/docker_utils.py
ignutils/draw_utils.py
ignutils/file_utils.py
ignutils/filter_utils.py
ignutils/fisheye_utils.py
ignutils/geom_utils.py
ignutils/img_utils.py
ignutils/json_utils.py
ignutils/keyboard_utils.py
ignutils/labelme_utils.py
ignutils/license_check.py
ignutils/mouse_utils.py
ignutils/multi_process_utils.py
ignutils/show_utils.py
ignutils/system_utils.py
ignutils/timer_utils.py
ignutils/typehint_utils.py
ignutils/yaml_utils.py
ignutils/segmentation_utils/edge_sam/setup.py
ignutils/segmentation_utils/edge_sam/segment_anything/__init__.py
ignutils/segmentation_utils/edge_sam/segment_anything/automatic_mask_generator.py
ignutils/segmentation_utils/edge_sam/segment_anything/build_sam.py
ignutils/segmentation_utils/edge_sam/segment_anything/predictor.py
ignutils/segmentation_utils/edge_sam/segment_anything/modeling/__init__.py
ignutils/segmentation_utils/edge_sam/segment_anything/modeling/common.py
ignutils/segmentation_utils/edge_sam/segment_anything/modeling/image_encoder.py
ignutils/segmentation_utils/edge_sam/segment_anything/modeling/mask_decoder.py
ignutils/segmentation_utils/edge_sam/segment_anything/modeling/prompt_encoder.py
ignutils/segmentation_utils/edge_sam/segment_anything/modeling/rep_vit.py
ignutils/segmentation_utils/edge_sam/segment_anything/modeling/sam.py
ignutils/segmentation_utils/edge_sam/segment_anything/modeling/transformer.py
ignutils/segmentation_utils/edge_sam/segment_anything/onnx/__init__.py
ignutils/segmentation_utils/edge_sam/segment_anything/onnx/predictor_onnx.py
ignutils/segmentation_utils/edge_sam/segment_anything/utils/__init__.py
ignutils/segmentation_utils/edge_sam/segment_anything/utils/amg.py
ignutils/segmentation_utils/edge_sam/segment_anything/utils/coreml.py
ignutils/segmentation_utils/edge_sam/segment_anything/utils/transforms.py
ignutils/segmentation_utils/sam/sam_infer.py
ignutils-0.0.11.dist-info/METADATA
ignutils-0.0.11.dist-info/WHEEL
ignutils-0.0.11.dist-info/top_level.txt
ignutils-0.0.11.dist-info/RECORD
