Metadata-Version: 2.1
Name: ignutils
Version: 0.0.11
Summary: Reusable components
Author-email: "Ignitarium Technology Solutions Pvt. Ltd." <jerin.antony@ignitarium.com>
Project-URL: Homepage, https://gitlab.ignitarium.in/ign-ai/internal/ignutils
Project-URL: Issues, https://gitlab.ignitarium.in/ign-ai/internal/ignutils/-/issues
Classifier: Programming Language :: Python :: 3
Classifier: License :: OSI Approved :: MIT License
Classifier: Operating System :: OS Independent
Requires-Python: >=3.8
Requires-Dist: bagpy
Requires-Dist: cryptography
Requires-Dist: cv-bridge
Requires-Dist: docker
Requires-Dist: easyprocess
Requires-Dist: fabulous
Requires-Dist: GitPython
Requires-Dist: GPUtil
Requires-Dist: imgaug
Requires-Dist: imutils
Requires-Dist: loguru
Requires-Dist: lsb-release-ex
Requires-Dist: matplotlib
Requires-Dist: ntplib
Requires-Dist: numpy
Requires-Dist: opencv-python
Requires-Dist: open3d
Requires-Dist: pandas
Requires-Dist: Pillow
Requires-Dist: pyautogui
Requires-Dist: pynput
Requires-Dist: pynvml
Requires-Dist: pyrealsense2
Requires-Dist: pyvirtualdisplay
Requires-Dist: scikit-image
Requires-Dist: selenium
Requires-Dist: shapely
Requires-Dist: sympy
Requires-Dist: termcolor
Requires-Dist: bs4
Requires-Dist: scipy
Requires-Dist: segment-anything
Requires-Dist: transformers
